testing_containers/__init__.py
testing_containers/docker_container.py
testing_containers/models.py
testing_containers/postgres/__init__.py
testing_containers/postgres/postgres_docker_container.py
testing_containers/postgres/postgres_manager.py
testing_containers/postgres/testing_postgres.py
testing_containers-0.3.1.dist-info/LICENSE
testing_containers-0.3.1.dist-info/METADATA
testing_containers-0.3.1.dist-info/WHEEL
testing_containers-0.3.1.dist-info/RECORD
