Metadata-Version: 2.1
Name: testing-containers
Version: 0.3.1
Summary: Spin up an isolated PostgreSQL test database (reusing local PG or Docker) with zero external service requirements for your test run.
Home-page: https://github.com/tedicela/testing-containers
License: MIT
Keywords: postgresql,testing,pytest,docker,alembic
Author: Tedi Cela
Author-email: tedicela@gmail.com
Requires-Python: >=3.10,<4.0
Classifier: Development Status :: 4 - Beta
Classifier: Intended Audience :: Developers
Classifier: License :: OSI Approved :: MIT License
Classifier: Programming Language :: Python :: 3
Classifier: Programming Language :: Python :: 3.10
Classifier: Programming Language :: Python :: 3.11
Classifier: Programming Language :: Python :: 3.12
Classifier: Programming Language :: Python :: 3.13
Classifier: Topic :: Software Development :: Testing
Classifier: Typing :: Typed
Requires-Dist: psycopg (>=3.2.0,<4.0.0)
Requires-Dist: pydantic (>=2.8.0,<3.0.0)
Project-URL: Repository, https://github.com/tedicela/testing-containers
